sleek_lvalert/__init__.py
sleek_lvalert/_version.py
sleek_lvalert/certs.pem
sleek_lvalert/tool.py
sleek_lvalert-2.0.0.dist-info/LICENSE.md
sleek_lvalert-2.0.0.dist-info/METADATA
sleek_lvalert-2.0.0.dist-info/WHEEL
sleek_lvalert-2.0.0.dist-info/entry_points.txt
sleek_lvalert-2.0.0.dist-info/top_level.txt
sleek_lvalert-2.0.0.dist-info/RECORD
