Metadata-Version: 2.1
Name: sleek-lvalert
Version: 2.0.0
Summary: LIGO/Virgo LVAlert client powered by SleekXMPP
Home-page: https://git.ligo.org/emfollow/sleek-lvalert
Author: Leo Singer
Author-email: leo.singer@ligo.org
License: GPL-3+
Platform: UNKNOWN
Classifier: Development Status :: 5 - Production/Stable
Classifier: Environment :: Console
Classifier: Intended Audience :: Science/Research
Classifier: License :: OSI Approved :: GNU General Public License v3 or later (GPLv3+)
Classifier: Operating System :: POSIX
Classifier: Programming Language :: Python :: 3
Classifier: Programming Language :: Python :: 3.5
Classifier: Programming Language :: Python :: 3.6
Classifier: Programming Language :: Python :: 3.7
Classifier: Programming Language :: Python :: 3.8
Classifier: Topic :: Internet
Classifier: Topic :: Scientific/Engineering :: Astronomy
Classifier: Topic :: Scientific/Engineering :: Physics
Requires-Dist: safe-netrc
Requires-Dist: slixmpp
